Metadata-Version: 2.1
Name: psfcube
Version: 0.10.0
Summary: psfcube: Python library to fit PSF profile + Background on Integral Field Unit cubes 
Home-page: https://github.com/MickaelRigault/psfcube
Download-URL: https://github.com/MickaelRigault/psfcube/0.10
Author: Mickael Rigault
Author-email: m.rigault@ipnl.in2p3.fr
Maintainer: Mickael Rigault
Maintainer-email: m.rigault@ipnl.in2p3.fr
License: Apache 2.0
Classifier: Intended Audience :: Science/Research
Classifier: Programming Language :: Python :: 2.7
Classifier: Programming Language :: Python :: 3.5
Classifier: License :: OSI Approved :: BSD License
Classifier: Topic :: Scientific/Engineering :: Astronomy
Classifier: Operating System :: POSIX
Classifier: Operating System :: Unix
Classifier: Operating System :: MacOS
License-File: LICENSE
